[{"No":0,"me":"Hehehehe ~!,School girls pussy ~! And the heart is all right ~!,,The cock is also gingin! !! Hahaha!"},{"No":1,"me":",It \u2019s my own, is n\u2019t it? ??,,Buhahahahaha! !!"},{"No":2,"me":",It \u2019s my own, is n\u2019t it? ??,,Buhahahahaha! !!"},{"No":3,"me":"After inserting the cock that Mr. Oji used from now on,,Ihihihi! !!,Hmmm!"},{"No":4,"me":"Hmmmm!"},{"No":5,"me":"Duha ~! \u2026 No, it \u2019s good!,It's a young pussy that still has hardness!,,Haha!"},{"No":6,"me":"A cock is inserted by Mr. Oji who is so old ...,Haha! It's the best! ?? Hmm! ??,,Uhe! To the top! !!"},{"No":7,"me":",This tightening condition! I can't stand it!"},{"No":8,"me":"Ah ~! Ah ~! It \u2019s good!,Hmm, it feels good to rub the cock! !!"},{"No":9,"me":"Kuu ~!,After all, if you commit, you're a school girl! Hahaha!,,Hmm, it burns!"},{"No":10,"me":"Oh! Oh ~! !!"},{"No":11,"me":",However, even if I faint, my pussy is stimulated, slowly,,I'm getting wet! Ah ~ I feel good! !!"},{"No":12,"me":"Kuhoo! !! Also, it \u2019s already dangerous! ...,I want to live! !! \u2026 Huh!,,I wonder where to ejaculate! ?? ..."},{"No":13,"me":"Hmm! Hah!,Let's pour semen into oh, oh, pussy! !!,,I'm pregnant with Oji-san's child! !!"},{"No":14,"me":"Hmm! Hah!,Or, let's throw semen on your body! !!,,Take a bath of Oji's semen! !!"},{"No":15,"me":"It \u2019s a pleasure ... Guhyu! ...,I've poured semen all the way to the back of my vagina! ...,,I'm sure I'm pregnant!,,,Gyahahahaha!"},{"No":16,"me":"Hi ... It's yabbee ~ It's too much semen ~,School girls covered with my semen! \u2026 Uhehehe!,,It's a view ~ My scent permeates my body,,,Nah ~ Guhahahaha!"},{"No":17,"me":""},{"No":18,"me":"Muhe ... I can't get up ...,,Let's play one more shot!,,,Ihihihihihihi! !!,Gollum!"},{"No":19,"me":"Muhe ...,I have to wake it up soon ...,,I don't know ..."},{"No":20,"me":""},{"No":21,"me":"Ah! Ahu!"},{"No":22,"me":"Oh! Ahi!"},{"No":23,"me":"Ugh! Ugh!"},{"No":24,"me":"Ahhhhhhhhh!"},{"No":25,"me":"Oh!"},{"No":26,"me":"Good luck!"},{"No":27,"me":"Kuu! Hagu!"},{"No":28,"me":"Go!"},{"No":29,"me":"Ugh!"},{"No":30,"me":"Hi! Oh! !!"},{"No":31,"me":"Ojyu! Aoooooooo ~"},{"No":32,"me":"Higu!"},{"No":33,"me":"Ah ~!"},{"No":34,"me":"Haha! !!"},{"No":35,"me":"Hmmmm!"},{"No":36,"me":""},{"No":37,"me":""},{"No":38,"me":""},{"No":39,"me":""},{"No":40,"me":"Nyuhehehehehe!,After all, the body of the athletic girl is different!,,I can't stop messing around!"},{"No":41,"me":"Mito-chan has a big body, but ...,The pussy is cute, isn't it? Pubic hair treated pie bread ...,,It's going to be tingling! Gollum! !!"},{"No":42,"me":"Well then ~ I'll put a cock ~!,Uhhhh! Uhehehehe!"},{"No":43,"me":"Uhi ~! Do not tighten it!,As expected, the muscles are different! Buhehehe!"},{"No":44,"me":"This is the body with the marks of this sunburn!,,I can see the LUK moving in my eyes ~ Hah!,I can't stand it!"},{"No":45,"me":"Ngu! Hi ~!,The pubic hair that is about to grow hits the cock!,,It's a pleasure!"},{"No":46,"me":"Ah ~ Great ~!,The pussy comes in close contact with the cock! ...,,Hahahaha!"},{"No":47,"me":"Hmmmm! Great! Ugh!"},{"No":48,"me":"With my large amount of cowper, the inside of the vagina is squeaky!,Oh ~ It \u2019s the best!"},{"No":49,"me":"Ahhhhh! It \u2019s out!,It's ejaculation! Hahaha! Kuho ~!,,Where should I throw it? ..."},{"No":50,"me":"Hihii! Oh, it's a pussy ...,Ejaculate in the pussy!,,Nah, vaginal cum shot! ..."},{"No":51,"me":"Hihii! Well, I'm gonna throw it outside! ...,I'll cover my back with semen!,,Hmmmmmmmm! !!"},{"No":52,"me":"Higu! It \u2019s no good! ..."},{"No":53,"me":"Buhe ~! ...,My semen has completely spread in the pussy!,,Haha, this is 100% conceived ~,,,Buhahahaha! !!"},{"No":54,"me":",Let's go back! The back was sticky with semen ~!,,Uhihihihi! !!"},{"No":55,"me":""},{"No":56,"me":"Hmm ~,One more time ... I wonder if I'll do it again!,,I don't think I'll wake up yet!,,,Uhyahyahyahya! !!"},{"No":57,"me":"Hmm ~,I'm about to wake up ...,,Toko wants to ejaculate more, but it can't be helped ...,,,When I wake it up ..."},{"No":58,"me":""},{"No":59,"me":"Hmm! ?? ..."},{"No":60,"me":",This is a surprise! Peeing!,,It looks like the drink is still working!"},{"No":61,"me":"Oh! ??,Ku, shit! ??,,Ah! Ah, I got it!,,,Uhi ~~! !!"},{"No":62,"me":"Ah! !!,It's not dirty! !!"},{"No":63,"me":"Uho ~~~! !!,I'm sorry! !!,,Oh, I put it out in front of me! !!"},{"No":64,"me":"Goho! !! !! Ahu! !! !!,Kussa ~~~~~~~! !! !!,,Uhihihihihihi! !! !!"},{"No":65,"me":""},{"No":66,"me":""},{"No":67,"me":"Hehehehe ~!,Cheeky young lady-it's just like a pussy-,,Hahahaha!"},{"No":68,"me":"To expose such an awkward abomination to me as a janitor ...,Kukuku!"},{"No":69,"me":"How about panties?,Does it smell like that?,,Guhehehehe!"},{"No":70,"me":",Does it smell like that?,,Guhehehehe!"},{"No":71,"me":"Look at it ~ Hehehe!,My cock! I wanted to put it in your pussy and got an erection,,Hmmmm! Hahaha!"},{"No":72,"me":"I'm gonna put it in the crack from now on!,It's good to writhe with a poor man's cock who is a year away!,,Gyahahahaha!"},{"No":73,"me":"Oh ~ la ..."},{"No":74,"me":"Ahu ~! ... I got in!,Aha! Ahahahaha!"},{"No":75,"me":"Haha! Do you know! ??,This position is called Kinuta!,,Ahu!,,,The glans rubs violently on the inner wall on the butt side of the vagina! \u2026 Good!"},{"No":76,"me":"Cheeks!,You feel good too! ?? Hahaha!,,My cock! Ugh ..."},{"No":77,"me":"While sleeping, a middle-aged butt cock goes in and out of the pussy,You might have dreamed that you were doing it!,,Haha! Ah ~ I feel ..."},{"No":78,"me":"Kufu ~! Yabe ~! Good!"},{"No":79,"me":"The pussy is getting wet!,The habit of school girls makes me completely female! ...,,Hmmmm! ..."},{"No":80,"me":"Uhe! To Hehehe!,I want to live! !!,,I'll ejaculate! Hahaha! After taking out the semen! !!"},{"No":81,"me":"Haha! Oh, I'll ejaculate a lot on my pussy ~!,I'll have my cheeky daughter conceive my kid!,,You should be a mother that year!"},{"No":82,"me":"Haha! I'll take it outside!,After making it covered with semen, I'm grateful! !!,,Hmmmm! !!"},{"No":83,"me":",I've got plenty of my kid! !!,,This is sure to get pregnant! Congratulations on your pregnancy! !!,,,Gyahahahaha! !!"},{"No":84,"me":"Uhhhhhh! !!,Oh, it's covered with my semen! !!,,How are you, young lady! I'm happy! ??,,,I think that only I can have such an erotic experience! !!"},{"No":85,"me":""},{"No":86,"me":",I'll play more!,,You should taste the end of the bully!,,,Buhahahahahaha!"},{"No":87,"me":"Uh ... sorry ...,I wanted to get more out of it, but if I didn't wake it up, it would be bad ..."},{"No":88,"me":""},{"No":89,"me":"Oh ~! ??,Sho, pee! ..."},{"No":90,"me":"Hey hey hey!,It depends on me! I'm sorry!,,Haha!"},{"No":91,"me":",School girls covered in pee!,,I'm sorry!"},{"No":92,"me":"Gyohe! !!,But defecation! !! ...,,I've done it! !!"},{"No":93,"me":"The effect of the medicine will remain!,Buhe ~! !!"},{"No":94,"me":"Manma shit that a rich lady fainted!,It's a superb view! !!"},{"No":95,"me":""},{"No":96,"me":""},{"No":97,"me":"Ahhhhh! Oh, in front of me!,School girls who want to have sex! Hahaha!,,Well, do you want so much Oji-san's cock! ??,,,Gokun!"},{"No":98,"me":"But it's already Bing, so I'll put it in!,And don't be patient!"},{"No":99,"me":"Ughhhhh! Hahaha!,I put it in ~ I put it in ~!,,Oji-san I put a cock in the crack of a school girl!,,,It feels good! !!"},{"No":100,"me":"Riinan-chan feels good too! ??,From now on, the friction with the cock will make it even better!,,Oh, I'm acme! Hahahaha!"},{"No":101,"me":"Hmmmm! It \u2019s good ...,The texture of this inner wall! !!,,It's a pussy that doesn't feel like it's being used yet!,,,Fresh! Fresh! Hahaha!"},{"No":102,"me":",Ah ~! I'm addicted to active school girls!,,Happy! !!"},{"No":103,"me":"Kufu ~! Hahaha!,Oh, I think it's shaking with a nice feeling ~,,I think I can be a good mother!,,,Uhi! Uhihihi! !!"},{"No":104,"me":"Ah! Ah ~! Hahaha!"},{"No":105,"me":"Nhi ~!,I'm so excited! \u2026 Ah ~ Yabe\u2026,,So it looks like it will come out! ..."},{"No":106,"me":"Ah ~! I can not do it!,Then come out! Kufu! Noooo!,,Where should I go! ?? ..."},{"No":107,"me":",,Uhhhh! Uhehehe! !!,Let's plant the seeds! Ah!"},{"No":108,"me":",,Uhhhh! Uhehehe! !!,Let's throw Oji's sperm on that body!"},{"No":109,"me":"Ahhh ... Hey, super-feeling! ...,I got a vaginal cum shot in the pussy of a school girl!,,Fuha! Fuhahahaha! !!,,,Well, the best! !!"},{"No":110,"me":"Kuhaa ~ ... and it came out ~,It \u2019s a great amount, is n\u2019t it?,,Uhhhh, I'm crazy about semen!,,,Guhahahahaha! !!"},{"No":111,"me":""},{"No":112,"me":"Guhehehe! It looks like it \u2019s going to be cool again!,This time ... haha!,,How do you enjoy it! ?? Gokun! !!"},{"No":113,"me":"Kuu ... Another shot! I want to say that ...,If you don't wake up, you may wake up alone ...,,I can't help it."},{"No":114,"me":""},{"No":115,"me":""},{"No":116,"me":"Buhe ~! I wonder if it's a growing body ~?,Or has it stopped? Gokun!,,It's a treat!"},{"No":117,"me":"Haha, a figure that you can really feel the fainting rape of school girls!,I'm going to get angry with my cock!"},{"No":118,"me":"I'm gonna put it in ... For a pussy that isn't ripe yet ...,Middle-aged old man's cock! ...,,Hahahaha! !!"},{"No":119,"me":"Kuho! !! ..."},{"No":120,"me":"Ah ~! Afufufu! !! ..."},{"No":121,"me":",Oh, it's blue! The inner wall is still too blue and hard ...,,However, I can't stand this! !! ..."},{"No":122,"me":"Good! !!,I have to get used to it ~ The pussy is put in and out of the cock like this,,If you don't do it, you won't feel well!,,,Uhehehe ~!"},{"No":123,"me":"I'll teach you to feel good about sex ...,I'm a cock ...,,Hahahaha!"},{"No":124,"me":"Ah ~ My cowper juice overflows a lot ...,It smells indescribable when mixed with this child's body fluids ...,,Ah ~! I'm so excited!"},{"No":125,"me":"Ohhhhh! Hahaha! !!"},{"No":126,"me":"How is it! ?? Sex feels good! ??,What! ?? Oh, my cock feels good! ??"},{"No":127,"me":"Kufu! \u2026 No, yabe,I want to live! !! Ah!,,Where are you going to go ..."},{"No":128,"me":"Haha! Sperm in the vagina ...,Let's inject my offspring! !! !! Ahhh!"},{"No":129,"me":"Haha! Let's put my sperm on my back!,Let's bukkake on your back! !!,,Ahhh!"},{"No":130,"me":"Fuhi ~ haha \u200b\u200b... buha!,The semen that was vaginal cum shot overflowed! Uhehehehehe!,,A semen pool has been created in the ass!,,,Guhahahahaha! !!"},{"No":131,"me":"Fuhi ~ haha \u200b\u200b... buha!,It came out a lot ~ Isn't my back chubby ~!,,Guhahahahaha! !!"},{"No":132,"me":""},{"No":133,"me":"Uhehehe! Another shot! I'll pull out another one!,With your blue body!,,Haha!"},{"No":134,"me":"Unu ...,Is it already the limit? ...,,If I don't wake it up, I feel like I'm about to wake up ...,,,it's no use\u2026"},{"No":135,"me":""},{"No":136,"me":"Ah! ?? Ah ~! ..."},{"No":137,"me":"Good luck!,I got pee! Hahaha!,,I wonder if I had sex and my bladder was loose! ??"},{"No":138,"me":"Ah ~ The smell of ammonia! Ammonia smell of school girls ~!,Haha! I can't stand it!"},{"No":139,"me":"!! ?? Hmm! ?? ...,Hey hey hey! Poop! Poop came out! !!,,Great! ..."},{"No":140,"me":"Goho! !! !! Oh! !!,Kussa ~! !! Raw shit of school girls!,,It's a freshly put out poop! !!,,,Guhaa! !! Buhehehehehehe! !!"},{"No":141,"me":"It's a bummer ...,I just deflated the feces, but I wonder if it will come out! ??,,Guhyahyahyahya! !!"},{"No":142,"me":""},{"No":143,"me":""},{"No":144,"me":"Nuhehe ~!,Tokiko ~ It's your favorite cock ~!,,Anyone can do it as long as they have a cock! ??,,,Guhyahyahya!"},{"No":145,"me":"Covered with my pee ~,It's a dirty teacher ~ Ihihihihi!"},{"No":146,"me":"Pee leaked ...,It smells fluffy ~ Ah ~ Kussa ~!"},{"No":147,"me":",It smells fluffy ~ Ah ~ Kussa ~!"},{"No":148,"me":",It smells fluffy ~ Ah ~ Kussa ~!"},{"No":149,"me":"I put panties on my head, so I recommend you to sniff it too!,Gyahahahaha!"},{"No":150,"me":"I had a diaper on my head, so the teacher should also sniff it!,Gyahahahaha!"},{"No":151,"me":"The body of a whip whip that started to get fat ...,A woman gives birth to a kid, isn't it?,,Hehehe ... Gokun!"},{"No":152,"me":"Well, the angry cock other than the host ...,I'll put it in!"},{"No":153,"me":"Oops!"},{"No":154,"me":"Ahu Ahu ~!"},{"No":155,"me":"Hehehe ~! It \u2019s easy to get in!,However, it's an exquisite wrapping ..."},{"No":156,"me":"Ahhhhh! Uhehe!,not bad! It's not bad!,,It feels like a pussy that I started to use!"},{"No":157,"me":"It fits perfectly! Ugh!,It feels good!"},{"No":158,"me":"Well, it's like putting a cock in a luxury masturbator,A sense of stability!,,Ah ~! Good! Kuha!,,,Hahahaha! !!"},{"No":159,"me":"Ah! Hahaha! Kufu ~!,Shake, shake! Fat sways!"},{"No":160,"me":"Good! ?? It \u2019s good for me! ??,It would be better than the host! Hahaha! !!,,Oh, panting! Make a good voice and cry! !!,,,Ugh ..."},{"No":161,"me":"Good, Tokiko! It looks like it \u2019s going to be good!,Ugh! I'll put it out, I'll put it out! !!"},{"No":162,"me":"Kuhi! Ma, it's a pussy! I'll put it out in the pussy!,The second kid is my DNA! !!,,Hmmmm! !! !!"},{"No":163,"me":",,Hmmmm! !! !!,Let my semen soak into my loose body! !!"},{"No":164,"me":"Fuhaaaa ~ ...,Yeah, I've had sex with me as a janitor ~ Teacher ...,,Creampie for a married woman, Guhe! Guhehehe ~!,,,Please conceive my child!"},{"No":165,"me":"Fuhaaaa ~ ...,Yeah, I've had sex with me as a janitor ~ Teacher ...,,I bukkake semen on the health teacher!,,,Every time you see you at the school, you will get an erection!"},{"No":166,"me":""},{"No":167,"me":",Let's do it again!,,Because such a whip whip fell down in front of me!,,,Haha!"},{"No":168,"me":",I'd like to say it again, but I wake up when it's time to wake up,,It could be ..."},{"No":169,"me":""},{"No":170,"me":"Umm ...,Sho, I want to pee ~,,Gokun!"},{"No":171,"me":"Uhehehehe ~!,Tokiko ~ ...,,I was leaking pee, so I got wet with a flashy pee,,,Is it? Hahaha!"},{"No":172,"me":"Ah ~ It was refreshing ~! !!"},{"No":173,"me":"Buha! Buhahahahaha! !!,Oh, my pee is covered! It's a nice view!,,Don't catch a cold, Tokiko ~! !!"},{"No":174,"me":"I thought I'd give it a piss shower, but I stopped,I'll do it ~ Guhehe!"},{"No":175,"me":""},{"No":176,"me":""},{"No":177,"me":",I wore a diaper and came over ~,,I was worried about incontinence! ??"},{"No":178,"me":",It's a beautiful shaved pussy!,,The soft hair is intriguing!"},{"No":179,"me":"Hahahaha!,The cracks are moist and moist ..."},{"No":180,"me":"The drifting ammonia odor makes my head flutter.,For a pussy that has just been incontinent ... Gokun!,,Oh, oh, my erection cock ..."},{"No":181,"me":"Kuhoo ~~~! !! !!"},{"No":182,"me":"This, the indescribable soft roughness of the inner wall of this pussy,Feeling hot, warm ...,,It wraps my cock and sticks to it! ..."},{"No":183,"me":"Come on, feel good! !!"},{"No":184,"me":"Oh! Cheeks!,Yabe ~ The cock is happy!,,Well, it's a year's pussy!"},{"No":185,"me":"It's the best ~, I thrust a cock into the pussy of a lot of school girls,It's done, but this guy is a good salt plum!,,Hahahaha!"},{"No":186,"me":"This feeling of elasticity ... It's something unique to Wakasa!,Ahhh! I can't stand it! ..."},{"No":187,"me":"It's a good pussy ~ Ah ~ Good!,The best! Uhhhh! Kuhi ~!"},{"No":188,"me":"After all, the green-smelling crack is the best!,Ugh! I, Iki! Ah! Ahh! !! !!"},{"No":189,"me":"No more peaches! !!,Well, let's go out! Hahahaha! !! !!"},{"No":190,"me":"Pussy! !! !! Let it go to the pussy! !! !!"},{"No":191,"me":"Bukkake, bukkake! Oops!"},{"No":192,"me":""},{"No":193,"me":"I've done it ~ Ahhh ~ ...,I got a vaginal cum shot in my daughter's vagina for a year ~,,This girl is pregnant and will fall ..."},{"No":194,"me":"Gyahahahaha! !!"},{"No":195,"me":"Jo, in the first year of school girls, I got a lot of semen bukkake,Ze ~ Fuhi ~ ...,,This guy seems to have a hard time wiping it off ..."},{"No":196,"me":"I want to have more fun with my 1st year daughter, but I have to wake up soon,Maybe it \u2019s bad ..."},{"No":197,"me":""},{"No":198,"me":""},{"No":199,"me":""},{"No":200,"me":""},{"No":201,"me":""},{"No":202,"me":""},{"No":203,"me":""},{"No":204,"me":""},{"No":205,"me":""},{"No":206,"me":""},{"No":207,"me":""},{"No":208,"me":""},{"No":209,"me":""},{"No":210,"me":""},{"No":211,"me":""},{"No":212,"me":""},{"No":213,"me":""},{"No":214,"me":""},{"No":215,"me":""},{"No":216,"me":""},{"No":217,"me":""},{"No":218,"me":""},{"No":219,"me":""},{"No":220,"me":""},{"No":221,"me":""},{"No":222,"me":""},{"No":223,"me":""},{"No":224,"me":""},{"No":225,"me":""},{"No":226,"me":""},{"No":227,"me":""},{"No":228,"me":""},{"No":229,"me":""},{"No":230,"me":""},{"No":231,"me":""},{"No":232,"me":""},{"No":233,"me":""},{"No":234,"me":""},{"No":235,"me":""},{"No":236,"me":""},{"No":237,"me":""},{"No":238,"me":""},{"No":239,"me":""},{"No":240,"me":""},{"No":241,"me":""},{"No":242,"me":""},{"No":243,"me":""},{"No":244,"me":""},{"No":245,"me":""},{"No":246,"me":""},{"No":247,"me":""},{"No":248,"me":""},{"No":249,"me":""},{"No":250,"me":""},{"No":251,"me":""},{"No":252,"me":""},{"No":253,"me":""},{"No":254,"me":""},{"No":255,"me":""},{"No":256,"me":""},{"No":257,"me":""},{"No":258,"me":""},{"No":259,"me":""},{"No":260,"me":""},{"No":261,"me":""},{"No":262,"me":""},{"No":263,"me":""},{"No":264,"me":""},{"No":265,"me":""},{"No":266,"me":""},{"No":267,"me":""},{"No":268,"me":""},{"No":269,"me":""},{"No":270,"me":""},{"No":271,"me":""},{"No":272,"me":""},{"No":273,"me":""},{"No":274,"me":""},{"No":275,"me":""},{"No":276,"me":""},{"No":277,"me":""},{"No":278,"me":""},{"No":279,"me":""},{"No":280,"me":""},{"No":281,"me":""},{"No":282,"me":""},{"No":283,"me":""},{"No":284,"me":""},{"No":285,"me":""},{"No":286,"me":""},{"No":287,"me":""},{"No":288,"me":""},{"No":289,"me":""},{"No":290,"me":""},{"No":291,"me":""},{"No":292,"me":""},{"No":293,"me":""},{"No":294,"me":""},{"No":295,"me":""},{"No":296,"me":""},{"No":297,"me":""},{"No":298,"me":""},{"No":299,"me":""},{"No":300,"me":""},{"No":301,"me":""},{"No":302,"me":""},{"No":303,"me":""},{"No":304,"me":""},{"No":305,"me":""},{"No":306,"me":""},{"No":307,"me":""},{"No":308,"me":""},{"No":309,"me":""},{"No":310,"me":""},{"No":311,"me":""},{"No":312,"me":""},{"No":313,"me":""},{"No":314,"me":""},{"No":315,"me":""},{"No":316,"me":""},{"No":317,"me":""},{"No":318,"me":""},{"No":319,"me":""},{"No":320,"me":""},{"No":321,"me":""},{"No":322,"me":""},{"No":323,"me":""},{"No":324,"me":""},{"No":325,"me":""},{"No":326,"me":""},{"No":327,"me":""},{"No":328,"me":""},{"No":329,"me":""},{"No":330,"me":""},{"No":331,"me":""},{"No":332,"me":""},{"No":333,"me":""},{"No":334,"me":""},{"No":335,"me":""},{"No":336,"me":""},{"No":337,"me":""},{"No":338,"me":""},{"No":339,"me":""},{"No":340,"me":""},{"No":341,"me":""},{"No":342,"me":""},{"No":343,"me":""},{"No":344,"me":""},{"No":345,"me":""},{"No":346,"me":""},{"No":347,"me":""},{"No":348,"me":""},{"No":349,"me":""},{"No":350,"me":""},{"No":351,"me":""},{"No":352,"me":""},{"No":353,"me":""},{"No":354,"me":""},{"No":355,"me":""},{"No":356,"me":""},{"No":357,"me":""},{"No":358,"me":""},{"No":359,"me":""},{"No":360,"me":""},{"No":361,"me":""},{"No":362,"me":""},{"No":363,"me":""},{"No":364,"me":""},{"No":365,"me":""},{"No":366,"me":""},{"No":367,"me":""},{"No":368,"me":""},{"No":369,"me":""},{"No":370,"me":""},{"No":371,"me":""},{"No":372,"me":""},{"No":373,"me":""},{"No":374,"me":""},{"No":375,"me":""},{"No":376,"me":""},{"No":377,"me":""},{"No":378,"me":""},{"No":379,"me":""},{"No":380,"me":""}]