[{"No":0,"me":",Stick out your tongue and blow bubbles!"},{"No":1,"me":",Let's jump out of the tongue!"},{"No":2,"me":",Blow bubbles from your mouth!"},{"No":3,"me":",I've done it ~ Pee!,,The pussy gets a cold ~,,,Gokun!"},{"No":4,"me":",I've done it ~ Poop!,,Poop is also attached to the pussy ~?,,,Gokun!"},{"No":5,"me":",,The pussy gets a cold ~,I've done it ~ Leaked!,,,Gokun!"},{"No":6,"me":",I've done it! Pee!,,I'm relieved because it's a diaper, but my crotch will be covered.,,,Yo ~!"},{"No":7,"me":",,I'm relieved because it's a diaper, but my crotch will be covered.,I've done it! Poop!,,,Yo ~!"},{"No":8,"me":",,I'm relieved because it's a diaper, but my crotch will be covered.,I've done it! Peeing!,,,Yo ~!"},{"No":9,"me":""},{"No":10,"me":"Do-re ...,Do you check the fainting condition?"},{"No":11,"me":""},{"No":12,"me":",Eyeballs are going up!,,It seems that two shots can be done with a margin!,,,Guhehehehe!"},{"No":13,"me":",,It seems that two shots can be done with a margin!,It \u2019s completely white!,,,Guhehehehe!"},{"No":14,"me":",If this is the case, it seems that two shots can be done with a margin!,,Guhehehehe!"},{"No":15,"me":"Hehehe ...,It seems that the degree is shallow ...,,Well, one shot can be done with a margin!,,,Guhehehehe!"},{"No":16,"me":"Well ...,I wonder if I can take it off even with clothes.,,Gollum!"},{"No":17,"me":",Let's do it with Clothes! ??,,Haha!"},{"No":18,"me":",Did you wear diapers ?!,,Hehehehehe! It \u2019s good!"},{"No":19,"me":"Oh ~ The diaper is cute ~!,Kuu ~ I can't stand patience ~!"},{"No":20,"me":",Kuu ~ I can't stand patience ~!"},{"No":21,"me":",Hey, you're young ~ The skin tension is different ~!,,I can't stop messing around!"},{"No":22,"me":"Ahe"},{"No":23,"me":"Ahhhh!"},{"No":24,"me":""},{"No":25,"me":",Oh, pussy! My cock in the pussy of a school girl ~!,,Hahahaha!"},{"No":26,"me":"I'll put it in! !!"},{"No":27,"me":""},{"No":28,"me":"Guhehehehe ~! !!,I rub the cock on my panties, so I like it!,,Hahahaha! !!"},{"No":29,"me":"However, this guy is a diaper ...,,You can even use diapers! I can do it!,,,Guhhhh! !!,Muhihihi!"},{"No":30,"me":""},{"No":31,"me":",Oh, my cock ... Let's taste it! ??,,Receive!"},{"No":32,"me":"Let's make school girls blowjob!"},{"No":33,"me":""},{"No":34,"me":",Or should I stop ..."},{"No":35,"me":""},{"No":36,"me":"Oh ...,I have something ..."},{"No":37,"me":"Hmm? This key!,Isn't it my toolbox! By the way ...,,This guy didn't want me to use the tools! ?? ..."},{"No":38,"me":""},{"No":39,"me":""},{"No":40,"me":"Aw\u2026,Did you put out a tongue and blow bubbles ...,,Kukuku!"},{"No":41,"me":"Aw\u2026,Bello is out ~,,Kukuku!"},{"No":42,"me":"Aw\u2026,Did you blow bubbles ...,,Kukuku!"},{"No":43,"me":",The crotch is peeing and peeing ~,,Intense ammonia odor ~ It's intriguing ~!"},{"No":44,"me":",The smell of poop is drifting from the crotch ~,,My nose seems to bend ... It's tempting!"},{"No":45,"me":",There is a mixed scent of pee and poop from the crotch,,Yeah ~,,,Goho! The nose seems to bend ... It's tempting!"},{"No":46,"me":",Even though it was put on a diaper, it has a strong ammonia odor.,,It's tempting!"},{"No":47,"me":",The eyeballs are pointing up ...,,If this is the case, it won't happen for a while ~"},{"No":48,"me":",,If this is the case, it won't happen for a while ~,White eyes, white eyes! It \u2019s completely crazy ..."},{"No":49,"me":"Ah ~ Isn't it good?,With this fainting condition, I won't get up for a while ~"},{"No":50,"me":"Ah ~ Well, this is ...,Anyway, I think I can enjoy one shot ...,,Gokun!"},{"No":51,"me":",Well then, I wonder if I should take off the clothes."},{"No":52,"me":"I'm excited enough as it is ...,Is this OK?"},{"No":53,"me":",Did you wear diapers ?!,,Hehehehehe! It \u2019s good!"},{"No":54,"me":"Isn't it nice to wear diapers?,Do you enjoy this! ??"},{"No":55,"me":",Do you enjoy this! ??"},{"No":56,"me":"After all, I think Supponpon is good! ??,Haha! What do you do! ??"},{"No":57,"me":"Another one! It looks like it!"},{"No":58,"me":"I want to have sex!,Sex with Oji-san!"},{"No":59,"me":",Don't throw it in!"},{"No":60,"me":""},{"No":61,"me":"Athlete daughter's panties ~!,,It \u2019s the best side dish!,Hahahaha!"},{"No":62,"me":"Oh, that's right.,This guy was a diaper ..."},{"No":63,"me":"But I'll do it!,Ihihihihi!"},{"No":64,"me":""},{"No":65,"me":",In the sweet and sour mouth of school girls ~,,Give off the smell of chestnut flowers, suck my cock,,,I'll give it to you!"},{"No":66,"me":""},{"No":67,"me":",Well, how can I enjoy it ..."},{"No":68,"me":""},{"No":69,"me":""},{"No":70,"me":"Oh! ??,I'm blowing bubbles with my tongue out! ...,,This is a good masterpiece ..."},{"No":71,"me":"Oh! ??,,This is a good masterpiece ...,I'm fainting with my tongue out! ..."},{"No":72,"me":"Oh! ??,Oh, did I blow bubbles and faint! ...,,It's a masterpiece ..."},{"No":73,"me":",The skirt has a pee stain on it!,,It's a nice view ~ Guhyahyahya!"},{"No":74,"me":",Is panties okay?,,The smell of poop is amazing! Guhyahya!"},{"No":75,"me":",The skirt has a pee stain on it!,,,It's a nice view ~ Guhyahyahya!,,The poop also smells ..."},{"No":76,"me":",I wonder if it's a diaper!,,It looks awkward ~ Guhyahyahya!"},{"No":77,"me":",,It looks awkward ~ Guhyahyahya!,I wonder if it's covered with diapers!"},{"No":78,"me":",,It looks awkward ~ Guhyahyahya!,I wonder if diapers are messed up!"},{"No":79,"me":"Hi!,Look up at the centerpiece ~,,This guy won't get up for a while! ..."},{"No":80,"me":"Hi!,,This guy won't get up for a while! ...,My eyes are white!"},{"No":81,"me":"Hi!,,This guy won't get up for a while! ...,It's completely cool ..."},{"No":82,"me":"Yabe ...,Fainting seems to be shallow ...,,However, one shot seems to be dangerous ..."},{"No":83,"me":",What about clothing clothes? ...,,Is it fun to peel it off?"},{"No":84,"me":",Will it be like this! ??,,If you do it, you're wearing clothes! ??"},{"No":85,"me":",Did you wear diapers ?!,,Hehehehehe! It \u2019s good!"},{"No":86,"me":",Do you wear diapers? ??,,It's a good idea not to take them all off ~"},{"No":87,"me":",,It's a good idea not to take them all off ~,Do you wear underwear! ??"},{"No":88,"me":",After all, if you do it, you're naked! ??,,Naked school girls! Kuu ~ Bing ~!"},{"No":89,"me":"I got an erection again!"},{"No":90,"me":",Inject my cock that feels good to cheeky school girls,,,Guhii!,,Let's give it!"},{"No":91,"me":",Even if it's a diaper, it's a diaper that keeps the warmth of school girls!,,A diaper soaked in the scent of a young girl's crack!,,,I'm so excited!"},{"No":92,"me":"Panties ~! Raw panties for school girls ~!,I'm going to have you become a side dish of masturbation from now on!,,I have to do it!"},{"No":93,"me":",Cock! I have to hold my cock in my mouth ~!,,It's delicious! Because delicious juice comes out ~!,,,Ahyahyahyahya!"},{"No":94,"me":""},{"No":95,"me":""},{"No":96,"me":""},{"No":97,"me":""},{"No":98,"me":"Hmm! ?? It \u2019s okay!,I'm blowing bubbles with a tongue out ~,,Great!"},{"No":99,"me":"Hmm! ?? It \u2019s okay!,I'm crazy with the tongue out ~,,Great!"},{"No":100,"me":"Hmm! ?? It \u2019s okay!,I'm bubbling,,Great!"},{"No":101,"me":"There is a pee pool!,,It's warm ~ It smells so good ~!,Hahahaha!"},{"No":102,"me":",It's warm ~ The smell of stool is amazing ~!,,Gohogoho! Intense ~!"},{"No":103,"me":"There is a pee pool!,,It's warm ~ The smell of stool is amazing ~!,Hahahaha!"},{"No":104,"me":"Is the diaper okay?,,It's warm ~ It smells so good ~!,Hahahaha!"},{"No":105,"me":",,Gohogoho! Intense ~!,It's warm ~ The smell of urine and stool is amazing ~!"},{"No":106,"me":"Oh!,Go up! Eyeball upwards!,,This guy has 2 shots confirmed!"},{"No":107,"me":"Oh!,,This guy has 2 shots confirmed!,White eyes! Peel off the white eyes ~!"},{"No":108,"me":"Oh!,,This guy has 2 shots confirmed!,It \u2019s not bad! It's a good salt plum!"},{"No":109,"me":"Oh ...,It's not bad, but is it limited to one shot at most? ..."},{"No":110,"me":",Well then, do you want to wear clothes?"},{"No":111,"me":",After all school girls are Clothes! ??,,Ji, the cock has a full erection ..."},{"No":112,"me":",Did you wear diapers ?!,,Hehehehehe! It \u2019s good!"},{"No":113,"me":",Ah, school girls wearing diapers ...,,Ji, the cock is rampaging quickly ..."},{"No":114,"me":",,Ji, the cock is rampaging quickly ...,Ah, school girls underwear ..."},{"No":115,"me":",Ah, naked school girls ...,,Yeah, my pants are cold in the first run ..."},{"No":116,"me":""},{"No":117,"me":"Hahahaha! I'll put it in!,Give my bottle cock to the cute crack!"},{"No":118,"me":"Do yoga in your dreams!,Gyahahahaha!"},{"No":119,"me":"Omuts worn by school girls!,A charming side dish that erects a cock just by saying that it has been used!,,Haha! Shi, chewy spree!"},{"No":120,"me":"The warmth and dampness of the crotch, the best with plenty of scent,Side dish!,,School girls panties ~! !!,,,It looks like a lot of semen will come out! !!"},{"No":121,"me":"A subtle expression that hasn't been formed yet, its lips ...,Put my stunning cock on my lips that don't feel like it! ..."},{"No":122,"me":"I'll insert it in my mouth!,Uhehehehe!"},{"No":123,"me":""},{"No":124,"me":""},{"No":125,"me":""},{"No":126,"me":""},{"No":127,"me":""},{"No":128,"me":",This girl sticks out her tongue and blows bubbles!,,I can't stand it!"},{"No":129,"me":",,I can't stand it!,This girl sticks out her tongue and falls down!"},{"No":130,"me":",,I can't stand it!,This girl has blown bubbles!"},{"No":131,"me":"School girls and pee!,It's an unbearable combination!,,It stirs up my desires!,,,Gokun!"},{"No":132,"me":"School girls and shit!,It's a kittsui combination!,,But it stirs up my desires!,,,Gokun!"},{"No":133,"me":",It's an unbearable combination!,,It stirs up my desires!,,,Gokun!"},{"No":134,"me":",It's an unbearable combination!,,It stirs up my desires!,,,Gokun!"},{"No":135,"me":",It's a kittsui combination!,,But it stirs up my desires!,,,Gokun!"},{"No":136,"me":",But it stirs up my desires!,,Gokun!"},{"No":137,"me":"Oh! Oh!,The eyeballs are facing up!,,If this is the case, I think I can enjoy two shots with plenty of room!,,,Uhihihihi!"},{"No":138,"me":"Oh! Oh!,,If this is the case, I think I can enjoy two shots with plenty of room!,There is no eyeball! It's white eyes!,,,Uhihihihi!"},{"No":139,"me":"Oh! Oh!,In this state, I think I can enjoy 2 shots with plenty of room!,,Uhihihihi!"},{"No":140,"me":"Oh! Oh ...,In this state, hmm ~,,Well, one shot is the limit ...,,,It can't be helped."},{"No":141,"me":"Alright!,Would you like to make this girl a soft-shelled turtle?,,Or ...,,,Gollum!"},{"No":142,"me":",Let's do it with the clothes on! ??,,What should I do! ??"},{"No":143,"me":",Did you wear diapers ?!,,Hehehehehe! It \u2019s good!"},{"No":144,"me":",,What should I do! ??,Let's keep wearing diapers! ??"},{"No":145,"me":",,What should I do! ??,Let's keep wearing underwear! ??"},{"No":146,"me":",,What should I do! ??,Let's make it a soft-shelled turtle! ??"},{"No":147,"me":"Yeah, it \u2019s not good! Another shot!"},{"No":148,"me":"See, the pussy of a school girl who seems to be small to see!,Oh, Oji's gently put in the chi, cock, cock,,I'll give it to you ~!"},{"No":149,"me":"Guhii! !!"},{"No":150,"me":",,I'll let you squeeze the cock with panties!,,,Oji-san is frustrated! Uhihihihi! !!,Pa, panties ~!"},{"No":151,"me":"Oops! ...,This girl was a diaper ... but you often have diapers,,The cock is OK because it looks good!,,,Gyahahaha!"},{"No":152,"me":",Have you ever sucked a cock?,,Oji's cock is delicious because it's seasoned!,,,Gyahahahaha!"},{"No":153,"me":""},{"No":154,"me":""},{"No":155,"me":""},{"No":156,"me":""},{"No":157,"me":""},{"No":158,"me":"Oh ~ I'm out tongue teacher!,Spider! \u2026 Guhahahaha!"},{"No":159,"me":"Oh ~ I'm out!,teacher! \u2026 Guhahahaha!"},{"No":160,"me":",teacher! \u2026 Guhahahaha!"},{"No":161,"me":"Muha! Muhahaha ~!,Teacher ~, I can't ...,,Let's pee!"},{"No":162,"me":"Muha! Muhahaha ~!,Se, Sensei ~ There is a scent of poop ~,,I can't ...,,,You leaked it ~ Hah!"},{"No":163,"me":"Muha! Muhahaha ~!,Teacher ~, I can't ...,,Let's leak pee ~ Gohogoho!,,,Oh, this smell! Is it shit too! ??"},{"No":164,"me":"Muha! Muhahaha ~!,Teacher ~, diapers ...,,You're peeing a lot ~?,,,Haha!"},{"No":165,"me":"Muha! Muhahaha ~!,Se, Sensei ~ There is a scent of poop ~,,I can't ...,,,I leaked it to a diaper ~"},{"No":166,"me":"Muha! Muhahaha ~!,Teacher ~, I can't ...,,,Oh, this smell! Is it shit too! ??,,Leak it on a diaper ~ Gohogoho!"},{"No":167,"me":",Eyeballs are looking up!,,Also, don't let the two shots go!,,,Hahahaha!"},{"No":168,"me":",,Also, don't let the two shots go!,You're white-eyed!,,,Hahahaha!"},{"No":169,"me":",,Also, don't let the two shots go!,You're fainting nicely!,,,Hahahaha!"},{"No":170,"me":"Let's teacher ...,With this amount, at most one shot ...,,Damn ..."},{"No":171,"me":",Then teacher ...,,Would you like to take off your clothes?"},{"No":172,"me":"Well, is this all right? ??,Let's do it soon!,,Hahahaha!"},{"No":173,"me":",Did you wear diapers ?!,,Hehehehehe! It \u2019s good!"},{"No":174,"me":"It's a whip whip, hey!,I'm gonna do it soon! what will you do! ??,,Hahahaha!"},{"No":175,"me":",I'm gonna do it soon! what will you do! ??,,Hahahaha!"},{"No":176,"me":""},{"No":177,"me":"Well ...,Shall I conceive the second person ~! ??,,You want a second person ~! ??,,,Raise my child as a couple!"},{"No":178,"me":",Adult diapers worn by the new wife ... Gokun!,,Ju, it's good enough as a side dish for masturbation!,,,I have to sprinkle semen in the diaper!"},{"No":179,"me":",Married woman's panties ... Gokun!,,I'm spitting! Rub the cock on the crotch,,,Ona Rimaku isn't it!"},{"No":180,"me":"Well, married woman ...,Let's chew on a cock other than the host ...,,Do you want it? You want to taste other cocks too! ??"},{"No":181,"me":"I'll make it come true! Guhihihihi!"},{"No":182,"me":",But another one! \u2026 Hahhhhh!"},{"No":183,"me":"I was wearing diapers ~ Teacher!,It's already a cock gingin!"},{"No":184,"me":""},{"No":185,"me":""},{"No":186,"me":"Hehehehehe!,I crouched down and fainted ...,,Gokun! !!"},{"No":187,"me":"Bello has popped out!,I've blown up the bubbles ..."},{"No":188,"me":"Bello has popped out!,Nuhe ~!"},{"No":189,"me":"Did you blow bubbles ?!,I'm very happy that Mr. Oji was so surprised.,,Ahihihihi!"},{"No":190,"me":"Hmm,School girls who have just leaked pee ~,,Ammonia odor that jumps into the nasal cavity causes the cock to burst,,,I just got an erection! ..."},{"No":191,"me":"Kuse ~,The smell of freshly shit from school girls! This is also a little hard,,It will make me even more excited! ...,,,The cock hurts because it erects too much!"},{"No":192,"me":"Kussa ~!,The vicious pungent odor of pee and poop spreads my nasal passages,,Come in! Buhehehe!,,,But it also raises my excitement to the top!"},{"No":193,"me":"The inside of the diaper is peeing, isn't it?"},{"No":194,"me":"If you leave it as it is, your crotch may become crazy,Yo ~"},{"No":195,"me":"Inside the diaper, the shit is sticking together,Would be?"},{"No":196,"me":"The inside of the diaper is peeing and pooping,Let's do it?"},{"No":197,"me":"Why don't you check Yume-chan's fainting condition ..."},{"No":198,"me":",Your eyes will turn up!,,If this is the case, two shots will be cool ..."},{"No":199,"me":",,If this is the case, two shots will be cool ...,It's white eyes White eyes! It \u2019s completely crazy ~"},{"No":200,"me":",,If this is the case, two shots will be cool ...,I like it! It \u2019s completely crazy ~"},{"No":201,"me":",It looks like I'm sleeping lightly ...,,Is this the limit for one shot? ..."},{"No":202,"me":"That's right ~,I wonder if I can take it off even with clothes.,,Hahhhhh ..."},{"No":203,"me":"I wonder if I can do it while wearing the clothes! ??,Gollum!"},{"No":204,"me":"Guhe ~! ??,I wore a diaper!,,It seems that he was worried about leaking it because he was sick!,,,Isn't it cute! Kukuku!"},{"No":205,"me":",It looks like a diaper, doesn't it look good? ??,,I can't stand it!"},{"No":206,"me":"Muhehe ~ In cute underwear ~!,Yo, it's going to overflow ...,,Gokun!"},{"No":207,"me":"Guhe ~! ??,I wore a diaper!,,It seems that he was worried about leaking it because he was sick!,,,Isn't it cute! Kukuku!"},{"No":208,"me":"Guhi ~! It's been a year off!,Hahahaha! But I can't stand it!,,The pants are messed up with the first run juice!"},{"No":209,"me":"Alright! Yo ~~!,I'll put it in, I'll put it in!,,Oji's angry cock is a 1st year school girl's pussy,,,Channi ~!"},{"No":210,"me":"Buhe! Buhehehe ~!,Ona with her 1st year daughter's innocent panties ...,,It's a diaper ~ Hey, if you use this diaper,,,It \u2019s amazing! ?? Gyahahahaha!"},{"No":211,"me":",,Let's enjoy rubbing a lot of cock!,Let's get on with the innocent panties of my 1st year daughter!"},{"No":212,"me":",Oji's cock is a lot older ...,,I'll put it in your mouth!,,,Ahhhh! This is exciting!"},{"No":213,"me":",Or should I stop ..."},{"No":214,"me":""},{"No":215,"me":""},{"No":216,"me":",It's only been a year, but the smell of girls is screaming ...,,It looks delicious!"},{"No":217,"me":"e! ??"},{"No":218,"me":"Eh! ??"},{"No":219,"me":"Ehhh! !! !! !! !! !! Oh, I got up! !!,It \u2019s dangerous! It \u2019s dangerous! !! What should I do! !!,,Nuoo! !!"},{"No":220,"me":"Zu, Zu, pants! I have to wear pants! !!"},{"No":221,"me":"No!"},{"No":222,"me":"Pants come first! !!"},{"No":223,"me":"Where's! ??"},{"No":224,"me":"Uo ~~! !!"},{"No":225,"me":"Huhuhu, what are you in a hurry?"},{"No":226,"me":"Hi, Oji-san ... I was asleep ..."},{"No":227,"me":"Unpleasant thing ..."},{"No":228,"me":"You were trying to do it ~?"},{"No":229,"me":"Ah! Ahh! This is a misunderstanding!,Misunderstanding! Yume-chan! Mr. Oji was ...,,(Well, what an excuse !?)"},{"No":230,"me":"Do you think you can escape by dressing like that?,Besides, I'm ... It's not a dream.,,My name is Mayu, Maya Momono, don't get me wrong."},{"No":231,"me":"Ha! ?? Well, Mayu! ?? ...,(This is what if !?),,(Is this child suffering from a sleep disorder !?)"},{"No":232,"me":"Ah, that, Mayu-san ...,Yume-san, Yume-san's consciousness is ...,,What's going on ..."},{"No":233,"me":"Hmm, a dream ~?,If you're that stupid, you're sleeping soundly.,,I am the one who controls this body now!,,,Mayu!"},{"No":234,"me":"Oh hey! ?? Is there such a thing! ??,Eh ...,,Well then, Yume-san doesn't notice this ...,,,Does that mean? \u2026 Gokun!"},{"No":235,"me":"Ahahaha!,You're surprisingly timid ~,,Fortunately or unfortunately, nothing happens when I dominate my body,,,I don't remember ..."},{"No":236,"me":"What is that ?! No ~ I was saved ~!,I was really scared ...,,Well then, will you go home with Yume-san on your behalf?"},{"No":237,"me":"Is that so?,This body has become a thing of Mayu ...,,Can't you enjoy it? Hey ..."},{"No":238,"me":"Yes! ??"},{"No":239,"me":"Oji-san, I'm showing my dick to me ...,Do you go home without doing anything?"},{"No":240,"me":"Hey ~ I and ..."},{"No":241,"me":"It feels good ... isn't it? ..."},{"No":242,"me":"Nah, Nah, Nani ~~~~! ?? !! ?? !! ??,Is this a dream! ??,,Is this me tempted by me ~! ??,,,This is the first time I've been born! ..."},{"No":243,"me":"I'm thrilled!,Moreover, I was tempted by a school girl ~~! !!,,Guhe! !! Guhehehe ~~~! !!"},{"No":244,"me":"Oji-san's getting smaller ...,It's getting really big ~"},{"No":245,"me":"Yume-chan, no Mayu-chan! ...,What should I do! ?? Hahahaha! !!,,(I don't know because I was always committing a daughter who doesn't move!)"},{"No":246,"me":"Huhhh, then ... lie down ..."},{"No":247,"me":"No! ..."},{"No":248,"me":""},{"No":249,"me":"that! ?? that! ?? Maya, Maya! ?? ...,Hey hey hey! ...,,No way! ?? Get up! ?? ..."},{"No":250,"me":"Maybe yabe!,It looks like the limit! ...,,I wanted to have more fun, but I'm sorry! ..."},{"No":251,"me":""},{"No":252,"me":""},{"No":253,"me":""},{"No":254,"me":""},{"No":255,"me":""},{"No":256,"me":""},{"No":257,"me":""},{"No":258,"me":""},{"No":259,"me":""},{"No":260,"me":""},{"No":261,"me":""},{"No":262,"me":""},{"No":263,"me":""},{"No":264,"me":""},{"No":265,"me":""},{"No":266,"me":""},{"No":267,"me":""},{"No":268,"me":""},{"No":269,"me":""},{"No":270,"me":""},{"No":271,"me":""},{"No":272,"me":""},{"No":273,"me":""},{"No":274,"me":""},{"No":275,"me":""},{"No":276,"me":""},{"No":277,"me":""},{"No":278,"me":""},{"No":279,"me":""},{"No":280,"me":""},{"No":281,"me":""},{"No":282,"me":""},{"No":283,"me":""},{"No":284,"me":""},{"No":285,"me":""},{"No":286,"me":""},{"No":287,"me":""},{"No":288,"me":""},{"No":289,"me":""},{"No":290,"me":""},{"No":291,"me":""},{"No":292,"me":""},{"No":293,"me":""},{"No":294,"me":""},{"No":295,"me":""},{"No":296,"me":""},{"No":297,"me":""},{"No":298,"me":""},{"No":299,"me":""},{"No":300,"me":""},{"No":301,"me":""},{"No":302,"me":""},{"No":303,"me":""},{"No":304,"me":""},{"No":305,"me":""},{"No":306,"me":""},{"No":307,"me":""},{"No":308,"me":""},{"No":309,"me":""},{"No":310,"me":""},{"No":311,"me":""},{"No":312,"me":""},{"No":313,"me":""},{"No":314,"me":""},{"No":315,"me":""},{"No":316,"me":""},{"No":317,"me":""},{"No":318,"me":""},{"No":319,"me":""},{"No":320,"me":""},{"No":321,"me":""},{"No":322,"me":""},{"No":323,"me":""},{"No":324,"me":""},{"No":325,"me":""},{"No":326,"me":""},{"No":327,"me":""},{"No":328,"me":""},{"No":329,"me":""},{"No":330,"me":""},{"No":331,"me":""},{"No":332,"me":""},{"No":333,"me":""},{"No":334,"me":""},{"No":335,"me":""},{"No":336,"me":""},{"No":337,"me":""},{"No":338,"me":""},{"No":339,"me":""},{"No":340,"me":""},{"No":341,"me":""},{"No":342,"me":""},{"No":343,"me":""},{"No":344,"me":""},{"No":345,"me":""},{"No":346,"me":""},{"No":347,"me":""},{"No":348,"me":""},{"No":349,"me":""},{"No":350,"me":""},{"No":351,"me":""},{"No":352,"me":""},{"No":353,"me":""},{"No":354,"me":""},{"No":355,"me":""},{"No":356,"me":""},{"No":357,"me":""},{"No":358,"me":""},{"No":359,"me":""},{"No":360,"me":""},{"No":361,"me":""},{"No":362,"me":""},{"No":363,"me":""},{"No":364,"me":""},{"No":365,"me":""},{"No":366,"me":""},{"No":367,"me":""},{"No":368,"me":""},{"No":369,"me":""},{"No":370,"me":""},{"No":371,"me":""},{"No":372,"me":""},{"No":373,"me":""},{"No":374,"me":""},{"No":375,"me":""},{"No":376,"me":""},{"No":377,"me":""},{"No":378,"me":""},{"No":379,"me":""},{"No":380,"me":""}]