[{"No":0,"me":"Wow!,It was funny! It was a mussel!"},{"No":1,"me":"That's right ~ Was it fun! It was good ~,(Kusso! Shiso ~! I failed to commit!),,(I wanted to dig into a black pussy ...)"},{"No":2,"me":"Come on, Yokatta! I'm proud of my friends!"},{"No":3,"me":"That\u2019s awesome!,It was fun! At first I was stupid,,Thank you Sumima Saen!"},{"No":4,"me":"Oh yeah ...,It was good, it was good ~ Ahaha ~ ..."},{"No":5,"me":"(Sorry! Have a chance to enjoy black school girls),(What do you miss! ...),,(Even if you regret it, you can't regret it! ...)"},{"No":6,"me":"That is ridiculous!,Is it Nan? ...,,Hmm ... That's why Japanese! \u2026 It \u2019s too boring!,,,Did you enjoy this? ??"},{"No":7,"me":"Eh ... I mean, I'm having fun ... Ugh ...,Su, Sumimasen ... (Goooooo ~~ !!),,(Why don't you get used to the American kid!)"},{"No":8,"me":"It's still better to watch Japanese TV, which has a low degree!"},{"No":9,"me":"Haha ...,(Guha!),,(No, I'm just pulling it right now and committing it! ...)"},{"No":10,"me":"Ah ...,Oh ... To, the toilet ... I want to go ..."},{"No":11,"me":"Oh! ?? What happened! ?? ...,(Buhe! It's a drink! ... Zama!)"},{"No":12,"me":"toilet! Where! ?? toilet! ... hahaha ..."},{"No":13,"me":"That? Somehow, it looks like an emergency! ?? ...,(Hihihihihi !!)"},{"No":14,"me":"Toilet, hmm ... I wonder if there was ...,For the time being-return to the starting point-?,,Uhhhh!"},{"No":15,"me":"Su, the starting point! Wow, I'll be back! ..."},{"No":16,"me":"Well, it's the worst! I was scared! \u2026 I'm already crazy!"},{"No":17,"me":"Well, don't get angry!,(I was fainted by another breath! ... sorry!)"},{"No":18,"me":"(I was a diaper and I was really saved!),(If I didn't have this, I would be very embarrassed by this time ...)"},{"No":19,"me":"(Ah ~, but the crotch is really disgusting ...)"},{"No":20,"me":"(Pa, pants are the worst!)"},{"No":21,"me":"Hmm? \u2026 That ~ It smells kind of ~,Hey, Molly-san, it smells like that, right?,,Is this shit? It smells like poop, right?"},{"No":22,"me":"Hmm? \u2026 That ~ It smells kind of ~,Hey, Molly-san, it smells like that, right?,,Is this pee? It smells like pee, right?"},{"No":23,"me":"Really?,I don't smell! Ne who doesn't smell!"},{"No":24,"me":"It's a janitor, this smell is from the janitor!"},{"No":25,"me":"Ha! ?? Eh! ?? That's it!"},{"No":26,"me":"I'm a janitor! This Japanese! Yaw, not me!"},{"No":27,"me":"Well, but ... that skirt ... Uhehe!,Gokun! !!"},{"No":28,"me":"Ha! Huh! !! !! ..."},{"No":29,"me":"No, no, no! Liar, shut up!,This was done by a janitor! Because of the janitor!,,The janitor is bad. The janitor is bad! !!"},{"No":30,"me":"Hi, yes, yes ... that's what ...,(Why! Shit! Americans! ...)"},{"No":31,"me":",That situation won't make it in time ~ Suffering ~! Hihihi!"},{"No":32,"me":"Hmmm.,Well, if that's the case, I'll do it somewhere before returning to the start,,Probably ... Hihihihi! !!"},{"No":33,"me":""},{"No":34,"me":""},{"No":35,"me":""},{"No":36,"me":"And before that, I have to put on the clothes and wake up!,Barre Barre."},{"No":37,"me":"Yes Yes! Do you want to put a suppository ?! ??,I wonder if I could put a suppository in the hole in the American ass! ??"},{"No":38,"me":"Well, what about this foreigner?,Wake it up or hold it back ...,,I have to wake it up ... I can still enjoy it ..."},{"No":39,"me":"Oops! Would you like to return with Molly in your arms ~!,However, it looks a little heavy ~ I'll do my best!"},{"No":40,"me":"Hunga! \u2026 What!,e! ?? I ... Hah! ?? ..."},{"No":41,"me":"Is that okay ~ Mr. Molly.,You were so scared that you fainted!,,Oh ~ hohohoho! !!"},{"No":42,"me":"Japanese is not good, and it's fainting!,Uhohoho ~!"},{"No":43,"me":"Oh, no!,You're lying to me!,I won't do it with this kind of Jap play! Absolutely!\nYou're lying to me!"},{"No":44,"me":"No, it's a bang ..."},{"No":45,"me":"No no, you lie! I'm lying!,I will tell the school teacher! !!"},{"No":46,"me":"e! ?? e! Hey, that's a little!,(Shit, what's this guy! ... It's a hassle!)"},{"No":47,"me":"I understand ~ You haven't fainted, right!,That's fine, right?,,I fell a little ~"},{"No":48,"me":"Yes!,That's right! Hahhh ..."},{"No":49,"me":"(Uh! ... It's bad !? Maybe!? ...),(Yaba! It's bad! I'm leaking pee!)"},{"No":50,"me":"(Uh! ... It's bad !? Maybe!? ...),(Yaba! It's bad! I'm leaking shit!)"},{"No":51,"me":"(Uh! ... It's bad !? Maybe!? ...),(Yaba! It's bad! I've leaked a lot!)"},{"No":52,"me":"(Ah! ... It's hard!),(Even the skirt is soaked!),,(That's why the janitor is grinning!)"},{"No":53,"me":"Hey, hey! Where are you looking! Hahaha!"},{"No":54,"me":"e! ?? Ehhh!,Because, Molly-san is leaking."},{"No":55,"me":"Well again! You're lying again!,No, I'll tell you, Ne!"},{"No":56,"me":"(Uhhhhh ...),Molly, I'll prepare to change clothes later!"},{"No":57,"me":"Besides, I'll keep this secret!,I can't lie to Japanese! (Hihihihi!)"},{"No":58,"me":"Come on, change clothes! ?? It \u2019s a secret death! Keep your promise!"},{"No":59,"me":"Okay, okay, when you have a problem, we are like each other ~,Uhehe, uhhh!,,Let's go back!"},{"No":60,"me":"(But I'm a diaper, so I'm saved ...),(Abunaa ~! ... I really hate Japan !!),,(Janitor, I'm looking at you with a lascivious face, and it's too disgusting!)"},{"No":61,"me":"(Guhe ~ It seems that you feel uncomfortable in your crotch ~!),(Suffering-Aggression and sickness-! Guhehehe!)"},{"No":62,"me":"Let's go back, Molly!"},{"No":63,"me":""},{"No":64,"me":""},{"No":65,"me":""},{"No":66,"me":"That's Molly's crotch, as you can see ...,Look, look closely ~"},{"No":67,"me":"Shut up!"},{"No":68,"me":",,I promised you for the time being ~,I can't tell from my mouth if it's there or why it's dirty."},{"No":69,"me":"This is necessary! ?? Report in front of everyone, necessary death ~! ??"},{"No":70,"me":"Ah ~ I need Arimasen ~! Uhehehe!,It's a joke, a joke ~,,Did you step on the dog poop? Uhe ~!"},{"No":71,"me":"Ah ~ Was it necessary Arimasen ~! ?? Uhehehe!,It's a joke, a joke ~~!"},{"No":72,"me":""},{"No":73,"me":""},{"No":74,"me":"Uhufu, I was scared, but it became fun to go!,I was stupid, but I wonder if I reviewed it ~ Jap!"},{"No":75,"me":"Ah ~ Really? Is this really the end?,Huh ~ It was a childish Jap event! !!,,Come and really regret death! !!"},{"No":76,"me":"I regret coming ...,It's hard to see a Jap event like this ...,,(No way, I'll leak it ...)"},{"No":77,"me":"I regret coming ...,I never thought that the Jap event was so cute,,Yo ~ ..."},{"No":78,"me":"(Somehow, my stomach hurts ...)"},{"No":79,"me":"I regret coming ... The Jap event is so cute,I didn't think about it ...,,(I'm so embarrassed that I can't tell anyone about fainting ...),,,(In addition ... it's leaking ... the worst!)"},{"No":80,"me":"(The butt is also tingling ...)"},{"No":81,"me":"I regret coming ... The Jap event is so cute,I didn't think about it ...,,(It's fainting and leaking ... the worst!),,,(It smells like pee all over my body! ... I want to cry ...)"},{"No":82,"me":"I regret coming ... The Jap event is so cute,I didn't think about it ...,,(It's fainting and leaking ... the worst!),,,(This is what I changed into ... I want to cry ...)"},{"No":83,"me":"Ah ... (Oh, it hurts, my stomach hurts ...)"},{"No":84,"me":"Hmm ...,(And because of fainting? ... I feel like my dick is getting very wet),,(Do ...)"},{"No":85,"me":"Hmm ...,(And because of fainting? ... I feel like my dick is getting very wet),,(Do ... and my face is tight ... Why!? ...)"},{"No":86,"me":"Hmm ...,(It feels like my mouth is sticky ... because of fainting? ...)"},{"No":87,"me":"Hmm ...,(It feels like my mouth is sticky ... because of fainting? ...),,(And my face is tight ... Why!? ...)"},{"No":88,"me":"Hmm ...,(You didn't leak it, right? ... but the diapers are cold ...)"},{"No":89,"me":"Hmm ...,(You didn't leak it, right? ... but the pants look cold ...)"},{"No":90,"me":"Hmm ...,(Ah, the diapers may be dangerous ... It's strangely messy ...)"},{"No":91,"me":"Hmm ...,(Ah, my pants may be dangerous ... It's strangely messy ...)"},{"No":92,"me":""},{"No":93,"me":""},{"No":94,"me":""},{"No":95,"me":",A moody female Tsura will come out!"},{"No":96,"me":"There! ??,you! Molly-san, isn't it?"},{"No":97,"me":"Huh! ?? ..."},{"No":98,"me":"Ugh, Janitor Jap! ..."},{"No":99,"me":"Ah, it's still a good way to speak ~ It's no good ~,What ...,,Yeah! ?? That stomach! What's wrong! ?? Uhhhh!"},{"No":100,"me":",You can see it by looking at it! You are a deliberate death!,,The cause is you in the first place!"},{"No":101,"me":"Giku! !! \u2026 e! ?? Doyu thing! ?? ..."},{"No":102,"me":"I've been scared of the night since I got sick of you!,So I started going to clubs ...,,Every time I get drunk, I have sex with a stranger! ...,,,Then ... Then ..."},{"No":103,"me":"Relieved ... (If you think it's out ...),Oh, that's why I was crazy with an unspecified number of people.,,Gokun!"},{"No":104,"me":"But you don't have to say such a thing out loud ~,Uhehehe ~!"},{"No":105,"me":"Shut up!,U, Ursai! Damare! Damn Jap! !!,,A small shit jap with a slanted eye! !! \u2026 Ugh"},{"No":106,"me":"Uh ~~~! !! !! ...,Hey, it's already Japan! Ugh! ..."},{"No":107,"me":"Oh ~ sorry ~ ...,Ahhhhhhhhhhhh ..."},{"No":108,"me":"Jap around me open their narrow eyes and look at you,Masuyo ~! Girojirojiro!"},{"No":109,"me":"Ah! Al hey, I remembered my business!,Well then, you're a master! Guhe ~!"},{"No":110,"me":"(Thank you for my kid ~ !! Half! Half!),(Half of blacks and unequaled! Raise properly!)"},{"No":111,"me":""},{"No":112,"me":""},{"No":113,"me":""},{"No":114,"me":"Nooooooooooooooooooooooooooooooooooooooooooooooooooooooooo !! !!,Gyaaaa! !! Oooooooooooooooooooooooooooooooooooooooooooooooooo !! !! Hmm ..."},{"No":115,"me":"Oh, oh ... mygaa ..."},{"No":116,"me":"\u2026\u2026\u2026"},{"No":117,"me":"What happened? ..."},{"No":118,"me":"Oh, there ..."},{"No":119,"me":"Did you surprise me too much! ?? I fainted!,Guhe ~! !!"},{"No":120,"me":"Just in case, I'm disguised!"},{"No":121,"me":"I'm sorry, I'm a big crotch ...,You can't see it in full view!,,Hihihi! Bo, erection, erection! !! ..."},{"No":122,"me":"Ugh! Chi, the cock was caught and I couldn't move!,Uhyahyahya! !!"},{"No":123,"me":"\u2026! !! Hmmmm! !! Yabe! !!,This is coming out! !! Yabe yabe ~! !!"},{"No":124,"me":"Up! !! !!"},{"No":125,"me":"Guha ~~~! !!"},{"No":126,"me":"Gofu! !! Buhohoho! !! This is a black school girl shit ...,Gohogoho! !!,,Kusse ~~! !!"},{"No":127,"me":"Hi ~! I took a shit shower on my face ~!"},{"No":128,"me":"Nuha ~! !!,One, additional pee kiter ~! !! Ah! Ah ~! !! !!"},{"No":129,"me":"Well, the best! !! !! Ugh! !! !!"},{"No":130,"me":"Buha! I'm suffocating!,Uhehehe ~! Hahaha! !!"},{"No":131,"me":"Nuha! !! Ugh! !! Kuu ~! !!"},{"No":132,"me":"Afuuu ~~~~ ..."},{"No":133,"me":"I've ejaculated ..."},{"No":134,"me":"Jo, covered with excrement of school girls, let's go without using hands,What ...,,Fuhi ~ I felt good ~ ..."},{"No":135,"me":""},{"No":136,"me":""},{"No":137,"me":""},{"No":138,"me":"Puhi ~!,My toys made in the United States are lying down!,,Muhe ~!"},{"No":139,"me":"Puhi ~!,,,Muhe ~!,American raw pussy! It felt good ~!,,If I have more time, I'll pour as many shots as I can!"},{"No":140,"me":"Puhi ~!,It's gaudy to get your futon dirty ~ It feels like America ~! ??,,Uha! Uha! Uha!"},{"No":141,"me":"Cheeks, cheeks! American!,All you can leak is hey! Guhaa! !!,,Isn't it loose here and there ?! ?? Gyahahaha!"},{"No":142,"me":"This is Mori ~! Are you still sleeping ~! ??,A playful American girl! If you don't get up, you'll commit,,Let's go! ?? Hihihihi!"},{"No":143,"me":""},{"No":144,"me":""},{"No":145,"me":""},{"No":146,"me":"Cheeks! American!,It's a pie that has grown steadily!"},{"No":147,"me":"Even if you look down on Japan, it doesn't matter!,However, you've already got my thing!,,Agyahahaha! !!"},{"No":148,"me":"Buhe ~! Oh, I dressed you up ~!,Thank you, Pudding Pudding's tits!"},{"No":149,"me":"Uhihi! How is it comfortable to wear? ??,It's my used briefs! Smell and pee and semen,,I can smell it! Hihihihi! !!"},{"No":150,"me":",I put on a towel so that I couldn't see the pussy!,,Hehe ~! I can't hide!"},{"No":151,"me":"Ushishi! Sheer bikini panties ~!,I can't see the cracks! Guhahahaha!"},{"No":152,"me":"Hmmm, it's my used shirt!,Uhh ~ The pussy isn't hidden ~!"},{"No":153,"me":"Hihihi! Uhi ~!,It's a naughty apron!,,Even if I don't wear it, I think I'll have this!"},{"No":154,"me":"Hihihi! Ku, bite, bite!,Swimsuit size small!,,I'm digging into my pussy!"},{"No":155,"me":"Kukuku! It looks shabby!,You can see the milk completely, and it looks good on you!"},{"No":156,"me":"Uhihi ~! Chito newspaper was small!,You can see the nipples! Uhyahyahya!"},{"No":157,"me":"Ushishi! The bikini is transparent!,You can see a crack in your nipple! Hahahaha!"},{"No":158,"me":"Muhe ~! The scent of breasts soaked into the bra!,I can't stand pa and panties!"},{"No":159,"me":"Muhe ~! This figure is a cloth diaper ~!,I can't stand the gap!"},{"No":160,"me":""},{"No":161,"me":""},{"No":162,"me":""},{"No":163,"me":"American school girls and Japanese old man Chu!,Uhe! Uhe! Uhhhh!"},{"No":164,"me":"These thick lips are surprisingly soft, huh!,And this scent ... I'm so excited!"},{"No":165,"me":"Npu ~! gulp! Uhhhh!,Ume ~ wow ~!"},{"No":166,"me":"After all school girls' lips are delicious! Hahaha! !!,I can't stand it ~ All the bodies around this age! ..."},{"No":167,"me":"Uhhhh, my sloppy, my brim in Molly's mouth ...,Haha! The cock is standing up! !!"},{"No":168,"me":"How is it ~! ??,The kiss with you made the cock look like this!,,Uhihihi ~!"},{"No":169,"me":"Feel my favorite with your face! Hahaha!"},{"No":170,"me":"Uhihi! Ihi ~!,It's Bing ~ It's pulsing!,,Rub it on your face and feel it!"},{"No":171,"me":"Hahhhhh!,My patience juice makes Molly's face slimy!,,Lustful Mori ~! Uhehehe ~!"},{"No":172,"me":""},{"No":173,"me":""},{"No":174,"me":""},{"No":175,"me":"Buhe! Gokun!"},{"No":176,"me":"Kukuku! Hahahaha!"},{"No":177,"me":"Kukuku! It's heavy in pee ~ hahahaha!"},{"No":178,"me":"Kukuku! It's heavy with poop ~ Hahahaha!"},{"No":179,"me":"Kukuku! It smells like shit ~ hahahaha!"},{"No":180,"me":",Good evening, pussy! Gokun!"},{"No":181,"me":"Uhehehehe ~! It's easier! ?? ..."},{"No":182,"me":"This is the last physical exchange with American school girls ...,Let's entertain!,,Guhe Guhe Guhe!"},{"No":183,"me":"You should also enjoy the erection cock of Japanese old man!,Hihihihi!"},{"No":184,"me":"Kuho! \u2026 Ohhhhh! !!"},{"No":185,"me":"Gokun! Nhu ~! Hafu ~! Hahaha!"},{"No":186,"me":"Ah ~! As expected, an American woman ...,It's deep ..."},{"No":187,"me":"However, the glans would have hit! ?? Uhihihihi! !! !!,Here!"},{"No":188,"me":"Uhehe, ah ~ I feel ... Americans are also in the middle ..."},{"No":189,"me":"Guhe ~! Ah ~ Good ~ This flesh ...,I can't stand it ..."},{"No":190,"me":"Warm American sex doll ~ haha!,It's been slimy ~ It's a nasty crack ~ ..."},{"No":191,"me":"Kufu, fu! Hahaha!,The big female body is also good ~ After all, the pussy got wet,,It's a female! Hahaha!"},{"No":192,"me":"Kuhi ~! It \u2019s good! Hahhhhhhh ~!"},{"No":193,"me":"Nucho Nucho! The pussy is slimy ~!,Ah ~ Ah ~ Yabe! It feels too good! !!"},{"No":194,"me":"Hafuhafu! !! Where is it good! ??,Are you pregnant! ?? Is it a semen shower! ?? Ah ~! ??"},{"No":195,"me":"Oops! Oh, conceive my child, my kid!"},{"No":196,"me":"Oops! Oh, take my semen with your whole body!"},{"No":197,"me":"Fugyahi! Ngafu!"},{"No":198,"me":"Ahu! Ngaa! !!"},{"No":199,"me":"Oh! Opu ~~~! !!"},{"No":200,"me":"Oh ~ Nho ~! Then it came out! Hahaha!"},{"No":201,"me":"Ya, it \u2019s dangerous! My semen is filled in the pussy,It's small! Uhya ~! !!,,pregnancy! Congratulations! Gyahahahaha! !!"},{"No":202,"me":"Hi-nbu! !!"},{"No":203,"me":"It was! What! !!"},{"No":204,"me":"Ngoo! Ah! !!"},{"No":205,"me":"Huh ~~~~! \u2026 Huh ~ Refreshing ~!,The ball bag is empty! ...,,Guhe! Guhe ~! Molly feels good ~! ??,,,Gyahahaha! !!"},{"No":206,"me":""},{"No":207,"me":""},{"No":208,"me":""},{"No":209,"me":"Ouch! Tummy ache!,Nguha ~! !! I, it \u2019s bad! !! Ah! !!"},{"No":210,"me":"Buhohoho! ?? e! ?? Eh! ?? What's wrong?,Muhihii ~! !!"},{"No":211,"me":"Toilet! Where is it! !! ...,Ugh! I'm going! !! Hahahaha! !! !!"},{"No":212,"me":""},{"No":213,"me":""},{"No":214,"me":""},{"No":215,"me":""},{"No":216,"me":""},{"No":217,"me":""},{"No":218,"me":""},{"No":219,"me":""},{"No":220,"me":""},{"No":221,"me":""},{"No":222,"me":""},{"No":223,"me":""},{"No":224,"me":""},{"No":225,"me":""},{"No":226,"me":""},{"No":227,"me":""},{"No":228,"me":""},{"No":229,"me":""},{"No":230,"me":""},{"No":231,"me":""},{"No":232,"me":""},{"No":233,"me":""},{"No":234,"me":""},{"No":235,"me":""},{"No":236,"me":""},{"No":237,"me":""},{"No":238,"me":""},{"No":239,"me":""},{"No":240,"me":""},{"No":241,"me":""},{"No":242,"me":""},{"No":243,"me":""},{"No":244,"me":""},{"No":245,"me":""},{"No":246,"me":""},{"No":247,"me":""},{"No":248,"me":""},{"No":249,"me":""},{"No":250,"me":""},{"No":251,"me":""},{"No":252,"me":""},{"No":253,"me":""},{"No":254,"me":""},{"No":255,"me":""},{"No":256,"me":""},{"No":257,"me":""},{"No":258,"me":""},{"No":259,"me":""},{"No":260,"me":""},{"No":261,"me":""},{"No":262,"me":""},{"No":263,"me":""},{"No":264,"me":""},{"No":265,"me":""},{"No":266,"me":""},{"No":267,"me":""},{"No":268,"me":""},{"No":269,"me":""},{"No":270,"me":""},{"No":271,"me":""},{"No":272,"me":""},{"No":273,"me":""},{"No":274,"me":""},{"No":275,"me":""},{"No":276,"me":""},{"No":277,"me":""},{"No":278,"me":""},{"No":279,"me":""},{"No":280,"me":""},{"No":281,"me":""},{"No":282,"me":""},{"No":283,"me":""},{"No":284,"me":""},{"No":285,"me":""},{"No":286,"me":""},{"No":287,"me":""},{"No":288,"me":""},{"No":289,"me":""},{"No":290,"me":""},{"No":291,"me":""},{"No":292,"me":""},{"No":293,"me":""},{"No":294,"me":""},{"No":295,"me":""},{"No":296,"me":""},{"No":297,"me":""},{"No":298,"me":""},{"No":299,"me":""},{"No":300,"me":""},{"No":301,"me":""},{"No":302,"me":""},{"No":303,"me":""},{"No":304,"me":""},{"No":305,"me":""},{"No":306,"me":""},{"No":307,"me":""},{"No":308,"me":""},{"No":309,"me":""},{"No":310,"me":""},{"No":311,"me":""},{"No":312,"me":""},{"No":313,"me":""},{"No":314,"me":""},{"No":315,"me":""},{"No":316,"me":""},{"No":317,"me":""},{"No":318,"me":""},{"No":319,"me":""},{"No":320,"me":""},{"No":321,"me":""},{"No":322,"me":""},{"No":323,"me":""},{"No":324,"me":""},{"No":325,"me":""},{"No":326,"me":""},{"No":327,"me":""},{"No":328,"me":""},{"No":329,"me":""},{"No":330,"me":""},{"No":331,"me":""},{"No":332,"me":""},{"No":333,"me":""},{"No":334,"me":""},{"No":335,"me":""},{"No":336,"me":""},{"No":337,"me":""},{"No":338,"me":""},{"No":339,"me":""},{"No":340,"me":""},{"No":341,"me":""},{"No":342,"me":""},{"No":343,"me":""},{"No":344,"me":""},{"No":345,"me":""},{"No":346,"me":""},{"No":347,"me":""},{"No":348,"me":""},{"No":349,"me":""},{"No":350,"me":""},{"No":351,"me":""},{"No":352,"me":""},{"No":353,"me":""},{"No":354,"me":""},{"No":355,"me":""},{"No":356,"me":""},{"No":357,"me":""},{"No":358,"me":""},{"No":359,"me":""},{"No":360,"me":""},{"No":361,"me":""},{"No":362,"me":""},{"No":363,"me":""},{"No":364,"me":""},{"No":365,"me":""},{"No":366,"me":""},{"No":367,"me":""},{"No":368,"me":""},{"No":369,"me":""},{"No":370,"me":""},{"No":371,"me":""},{"No":372,"me":""},{"No":373,"me":""},{"No":374,"me":""},{"No":375,"me":""},{"No":376,"me":""},{"No":377,"me":""},{"No":378,"me":""},{"No":379,"me":""},{"No":380,"me":""},{"No":381,"me":""},{"No":382,"me":""},{"No":383,"me":""},{"No":384,"me":""},{"No":385,"me":""},{"No":386,"me":""},{"No":387,"me":""},{"No":388,"me":""},{"No":389,"me":""},{"No":390,"me":""},{"No":391,"me":""},{"No":392,"me":""},{"No":393,"me":""},{"No":394,"me":""},{"No":395,"me":""},{"No":396,"me":""},{"No":397,"me":""},{"No":398,"me":""},{"No":399,"me":""},{"No":400,"me":""},{"No":401,"me":""},{"No":402,"me":""},{"No":403,"me":""},{"No":404,"me":""},{"No":405,"me":""},{"No":406,"me":""},{"No":407,"me":""},{"No":408,"me":""},{"No":409,"me":""},{"No":410,"me":""},{"No":411,"me":""},{"No":412,"me":""},{"No":413,"me":""},{"No":414,"me":""},{"No":415,"me":""},{"No":416,"me":""},{"No":417,"me":""},{"No":418,"me":""},{"No":419,"me":""},{"No":420,"me":""},{"No":421,"me":""},{"No":422,"me":""},{"No":423,"me":""},{"No":424,"me":""},{"No":425,"me":""},{"No":426,"me":""},{"No":427,"me":""},{"No":428,"me":""},{"No":429,"me":""},{"No":430,"me":""},{"No":431,"me":""},{"No":432,"me":""},{"No":433,"me":""},{"No":434,"me":""},{"No":435,"me":""},{"No":436,"me":""},{"No":437,"me":""},{"No":438,"me":""},{"No":439,"me":""},{"No":440,"me":""},{"No":441,"me":""},{"No":442,"me":""},{"No":443,"me":""},{"No":444,"me":""},{"No":445,"me":""},{"No":446,"me":""},{"No":447,"me":""},{"No":448,"me":""},{"No":449,"me":""},{"No":450,"me":""},{"No":451,"me":""},{"No":452,"me":""},{"No":453,"me":""},{"No":454,"me":""},{"No":455,"me":""},{"No":456,"me":""},{"No":457,"me":""},{"No":458,"me":""},{"No":459,"me":""},{"No":460,"me":""},{"No":461,"me":""},{"No":462,"me":""},{"No":463,"me":""},{"No":464,"me":""},{"No":465,"me":""},{"No":466,"me":""},{"No":467,"me":""},{"No":468,"me":""},{"No":469,"me":""},{"No":470,"me":""},{"No":471,"me":""},{"No":472,"me":""},{"No":473,"me":""},{"No":474,"me":""},{"No":475,"me":""},{"No":476,"me":""},{"No":477,"me":""},{"No":478,"me":""},{"No":479,"me":""},{"No":480,"me":""},{"No":481,"me":""},{"No":482,"me":""},{"No":483,"me":""},{"No":484,"me":""},{"No":485,"me":""},{"No":486,"me":""},{"No":487,"me":""},{"No":488,"me":""},{"No":489,"me":""},{"No":490,"me":""},{"No":491,"me":""},{"No":492,"me":""},{"No":493,"me":""},{"No":494,"me":""},{"No":495,"me":""},{"No":496,"me":""},{"No":497,"me":""},{"No":498,"me":""},{"No":499,"me":""},{"No":500,"me":""},{"No":501,"me":""},{"No":502,"me":""},{"No":503,"me":""},{"No":504,"me":""},{"No":505,"me":""},{"No":506,"me":""},{"No":507,"me":""},{"No":508,"me":""},{"No":509,"me":""},{"No":510,"me":""},{"No":511,"me":""},{"No":512,"me":""},{"No":513,"me":""},{"No":514,"me":""},{"No":515,"me":""},{"No":516,"me":""},{"No":517,"me":""},{"No":518,"me":""},{"No":519,"me":""},{"No":520,"me":""},{"No":521,"me":""},{"No":522,"me":""},{"No":523,"me":""},{"No":524,"me":""},{"No":525,"me":""},{"No":526,"me":""},{"No":527,"me":""},{"No":528,"me":""},{"No":529,"me":""},{"No":530,"me":""},{"No":531,"me":""},{"No":532,"me":""},{"No":533,"me":""},{"No":534,"me":""},{"No":535,"me":""},{"No":536,"me":""},{"No":537,"me":""},{"No":538,"me":""},{"No":539,"me":""},{"No":540,"me":""},{"No":541,"me":""},{"No":542,"me":""},{"No":543,"me":""},{"No":544,"me":""},{"No":545,"me":""},{"No":546,"me":""},{"No":547,"me":""},{"No":548,"me":""},{"No":549,"me":""},{"No":550,"me":""}]